biometric/t1.py
biometric/zk.py
common/apiv2.py
common/common.py
common/compression.py
common/data.py
common/databox.py
common/globals.py
common/http.py
common/json.py
common/logger.py
common/mailbox.py
common/mimeList.py
common/nlp.py
common/response.py
common/services.py
common/smtp.py
common/template.py
common/utils.py
database/connection.py
database/dbtable.py
database/mongo.py
database/oracle.py
database/sqlite.py
django/core.py
django/database.py
django/namingSequance.py
django/utils.py
google/firebase.py
gsk/Aadhar_Extractor.py
gsk/Pan_Extractor.py
gsk/common1.py
gsk/settings.py
gsk-1.0.1.data/scripts/dokr
gsk-1.0.1.data/scripts/gsk
gsk-1.0.1.data/scripts/gsk_script
ldap/auth.py
paymentGateway/razorpay.py
selenium/seleniumFacebook.py
selenium/seleniumLib.py
selenium/seleniumWhatsapp.py
ubuntu/scanimage.py
ubuntu/shell.py
ui/uiDoc.py
utils/jsonReport.py
gsk-1.0.1.dist-info/METADATA
gsk-1.0.1.dist-info/WHEEL
gsk-1.0.1.dist-info/top_level.txt
gsk-1.0.1.dist-info/RECORD
