Metadata-Version: 2.1
Name: gsk
Version: 1.0.1
Summary: A Library set of rapid application development
Home-page: 
Author: Shravan Kumar Gautam
Author-email: shravan.gautam@gmail.com
License: MIT
Platform: UNKNOWN
Classifier: Programming Language :: Python :: 3
Classifier: License :: OSI Approved :: MIT License
Classifier: Operating System :: OS Independent
Requires-Dist: Jinja2
Requires-Dist: cx-Oracle
Requires-Dist: simplejson
Requires-Dist: pymysql
Requires-Dist: websockets
Requires-Dist: websocket
Requires-Dist: pyperclip
Requires-Dist: flufl.bounce
Requires-Dist: lambda
Requires-Dist: requests
Requires-Dist: python-magic
